{
  "component": {
    "name": "career_highlight_item",
    "display_name": "Career Highlight Item",
    "is_nestable": true,
    "is_root": false,
    "schema": {
      "date_label": {
        "type": "text",
        "pos": 0,
        "translatable": true,
        "description": "Rango de fechas o texto de tiempo (ej. '2001 - 2004')."
      },
      "role_label": {
        "type": "text",
        "pos": 1,
        "translatable": true,
        "description": "Cargo o rol (ej. 'Principal Guest Conductor'). Se mostrará en pequeño y mayúsculas."
      },
      "description": {
        "type": "textarea",
        "pos": 2,
        "translatable": true,
        "description": "Breve descripción del logro o puesto."
      },
      "sort_order": {
        "type": "number",
        "pos": 3,
        "translatable": false,
        "description": "Campo numérico técnico para ordenación programática futura. No se renderiza."
      }
    }
  }
}
